<?xml version="1.0" encoding="UTF-8"?>

<FLOW VERSION="3.0" CLEANUP="true">
  <COMMENT>Specify and set the default parameter required during the execution of the flow</COMMENT>

  <!-- nodes -->

<MAP NAME="specifyDefaultSettings" MODE="STANDALONE">
  <COMMENT>Specify and set the default parameter required during the execution of the flow</COMMENT>
  <MAPTARGET>

<Values version="2.0">
  <record name="xml" javaclass="com.wm.util.Values">
    <value name="node_type">record</value>
    <value name="is_public">false</value>
    <value name="field_type">record</value>
    <value name="field_dim">0</value>
    <value name="nillable">true</value>
    <value name="form_qualified">false</value>
    <value name="is_global">false</value>
    <array name="rec_fields" type="record" depth="1">
      <record javaclass="com.wm.util.Values">
        <value name="node_type">unknown</value>
        <value name="is_public">false</value>
        <value name="field_name">$dbAlias</value>
        <value name="field_type">string</value>
        <value name="field_dim">0</value>
        <value name="nillable">true</value>
        <value name="form_qualified">false</value>
        <value name="is_global">false</value>
      </record>
      <record javaclass="com.wm.util.Values">
        <value name="node_type">record</value>
        <value name="is_public">false</value>
        <value name="field_name">ForecastBizDoc</value>
        <value name="field_type">recref</value>
        <value name="field_dim">0</value>
        <value name="nillable">true</value>
        <value name="form_qualified">false</value>
        <value name="is_global">false</value>
        <value name="modifiable">true</value>
        <value name="rec_ref">masterScheduling1213.intoOA.forecast.rec:ForecastBizDoc</value>
      </record>
      <record javaclass="com.wm.util.Values">
        <value name="node_type">unknown</value>
        <value name="is_public">false</value>
        <value name="field_name">OracleAppsUserName</value>
        <value name="field_type">string</value>
        <value name="field_dim">0</value>
        <value name="nillable">true</value>
        <value name="form_qualified">false</value>
        <value name="is_global">false</value>
      </record>
    </array>
    <value name="modifiable">true</value>
  </record>
</Values>
</MAPTARGET>
  <MAPSOURCE>

<Values version="2.0">
  <record name="xml" javaclass="com.wm.util.Values">
    <value name="node_type">record</value>
    <value name="is_public">false</value>
    <value name="field_type">record</value>
    <value name="field_dim">0</value>
    <value name="nillable">true</value>
    <value name="form_qualified">false</value>
    <value name="is_global">false</value>
    <array name="rec_fields" type="record" depth="1">
    </array>
    <value name="modifiable">true</value>
  </record>
</Values>
</MAPSOURCE>

  <!-- nodes -->

<MAPSET NAME="Setter" OVERWRITE="true" VARIABLES="false" GLOBALVARIABLES="false" FIELD="/OracleAppsUserName;1;0">
  <DATA ENCODING="XMLValues" I18N="true">

<Values version="2.0">
  <value name="xml">OPERATIONS</value>
  <record name="type" javaclass="com.wm.util.Values">
    <value name="node_type">unknown</value>
    <value name="is_public">false</value>
    <value name="field_name">OracleAppsUserName</value>
    <value name="field_type">string</value>
    <value name="field_dim">0</value>
    <value name="nillable">true</value>
    <value name="form_qualified">false</value>
    <value name="is_global">false</value>
  </record>
</Values>
</DATA>
</MAPSET>

<MAPSET NAME="Setter" OVERWRITE="true" VARIABLES="false" GLOBALVARIABLES="false" FIELD="/$dbAlias;1;0">
  <DATA ENCODING="XMLValues" I18N="true">

<Values version="2.0">
  <value name="xml">OracleAppsDB12</value>
  <record name="type" javaclass="com.wm.util.Values">
    <value name="node_type">unknown</value>
    <value name="is_public">false</value>
    <value name="field_name">$dbAlias</value>
    <value name="field_type">string</value>
    <value name="field_dim">0</value>
    <value name="nillable">true</value>
    <value name="form_qualified">false</value>
    <value name="is_global">false</value>
  </record>
</Values>
</DATA>
</MAPSET>
</MAP>

<SEQUENCE TIMEOUT="" EXIT-ON="SUCCESS">
  <COMMENT>Default Steps implemented for All Inbound Transactions</COMMENT>

  <!-- nodes -->

<SEQUENCE TIMEOUT="" EXIT-ON="FAILURE">
  <COMMENT>Main Logic Sequence - exit on failure</COMMENT>

  <!-- nodes -->

<INVOKE TIMEOUT="" SERVICE="masterScheduling1213.intoOA.forecast.custom:bizDocMapping" VALIDATE-IN="$none" VALIDATE-OUT="$none">
  <COMMENT>Business Document Mapping</COMMENT>

  <!-- nodes -->

<MAP MODE="INPUT">
</MAP>

<MAP MODE="OUTPUT">
  <MAPTARGET>

<Values version="2.0">
  <record name="xml" javaclass="com.wm.util.Values">
    <value name="node_type">record</value>
    <value name="is_public">false</value>
    <value name="field_type">record</value>
    <value name="field_dim">0</value>
    <value name="nillable">true</value>
    <value name="form_qualified">false</value>
    <value name="is_global">false</value>
    <array name="rec_fields" type="record" depth="1">
      <record javaclass="com.wm.util.Values">
        <value name="node_type">unknown</value>
        <value name="is_public">false</value>
        <value name="field_name">$dbAlias</value>
        <value name="field_type">string</value>
        <value name="field_dim">0</value>
        <value name="nillable">true</value>
        <value name="form_qualified">false</value>
        <value name="is_global">false</value>
      </record>
      <record javaclass="com.wm.util.Values">
        <value name="node_type">record</value>
        <value name="is_public">false</value>
        <value name="field_name">ForecastBizDoc</value>
        <value name="field_type">recref</value>
        <value name="field_dim">0</value>
        <value name="nillable">true</value>
        <value name="form_qualified">false</value>
        <value name="is_global">false</value>
        <value name="modifiable">true</value>
        <value name="rec_ref">masterScheduling12.intoOA.forecast.rec:ForecastBizDoc</value>
      </record>
      <record javaclass="com.wm.util.Values">
        <value name="node_type">unknown</value>
        <value name="is_public">false</value>
        <value name="field_name">OracleAppsUserName</value>
        <value name="field_type">string</value>
        <value name="field_dim">0</value>
        <value name="nillable">true</value>
        <value name="form_qualified">false</value>
        <value name="is_global">false</value>
      </record>
      <record javaclass="com.wm.util.Values">
        <value name="node_type">record</value>
        <value name="is_public">false</value>
        <value name="field_name">ForecastRecordSet</value>
        <value name="field_type">recref</value>
        <value name="field_dim">0</value>
        <value name="nillable">true</value>
        <value name="form_qualified">false</value>
        <value name="is_global">false</value>
        <value name="modifiable">true</value>
        <value name="rec_ref">masterScheduling12.intoOA.forecast.rec:setForecastTxnInputRec</value>
      </record>
    </array>
    <value name="modifiable">true</value>
  </record>
</Values>
</MAPTARGET>
  <MAPSOURCE>

<Values version="2.0">
  <record name="xml" javaclass="com.wm.util.Values">
    <value name="node_type">record</value>
    <value name="is_public">false</value>
    <value name="field_type">record</value>
    <value name="field_dim">0</value>
    <value name="nillable">true</value>
    <value name="form_qualified">false</value>
    <value name="is_global">false</value>
    <array name="rec_fields" type="record" depth="1">
    </array>
    <value name="modifiable">true</value>
  </record>
</Values>
</MAPSOURCE>

  <!-- nodes -->

<MAPDELETE NAME="Dropper" FIELD="/ForecastBizDoc;4;0;masterScheduling1213.intoOA.forecast.rec:ForecastBizDoc">
</MAPDELETE>

<MAPDELETE NAME="Dropper" FIELD="/OracleAppsUserName;1;0">
</MAPDELETE>
</MAP>
</INVOKE>

<INVOKE TIMEOUT="" SERVICE="masterScheduling1213.intoOA.forecast.custom:setForecastTxn" VALIDATE-IN="$none" VALIDATE-OUT="$none">
  <COMMENT></COMMENT>

  <!-- nodes -->

<MAP MODE="INPUT">
  <MAPTARGET>

<Values version="2.0">
  <record name="xml" javaclass="com.wm.util.Values">
    <value name="node_type">record</value>
    <value name="is_public">false</value>
    <value name="field_type">record</value>
    <value name="field_dim">0</value>
    <value name="nillable">true</value>
    <value name="form_qualified">false</value>
    <value name="is_global">false</value>
    <array name="rec_fields" type="record" depth="1">
      <record javaclass="com.wm.util.Values">
        <value name="node_type">record</value>
        <value name="is_public">false</value>
        <value name="field_name">setForecastTxnInput</value>
        <value name="field_type">record</value>
        <value name="field_dim">0</value>
        <value name="nillable">true</value>
        <value name="form_qualified">false</value>
        <value name="is_global">false</value>
        <array name="rec_fields" type="record" depth="1">
        </array>
        <value name="modifiable">true</value>
      </record>
      <record javaclass="com.wm.util.Values">
        <value name="node_type">record</value>
        <value name="is_public">false</value>
        <value name="field_name">$connectionName</value>
        <value name="field_type">string</value>
        <value name="field_dim">0</value>
        <value name="field_opt">true</value>
        <value name="nillable">false</value>
        <value name="form_qualified">false</value>
        <value name="is_global">false</value>
      </record>
    </array>
    <value name="modifiable">true</value>
  </record>
</Values>
</MAPTARGET>
  <MAPSOURCE>

<Values version="2.0">
  <record name="xml" javaclass="com.wm.util.Values">
    <value name="node_type">record</value>
    <value name="is_public">false</value>
    <value name="field_type">record</value>
    <value name="field_dim">0</value>
    <value name="nillable">true</value>
    <value name="form_qualified">false</value>
    <value name="is_global">false</value>
    <array name="rec_fields" type="record" depth="1">
      <record javaclass="com.wm.util.Values">
        <value name="node_type">unknown</value>
        <value name="is_public">false</value>
        <value name="field_name">$dbAlias</value>
        <value name="field_type">string</value>
        <value name="field_dim">0</value>
        <value name="nillable">true</value>
        <value name="form_qualified">false</value>
        <value name="is_global">false</value>
      </record>
      <record javaclass="com.wm.util.Values">
        <value name="node_type">record</value>
        <value name="is_public">false</value>
        <value name="field_name">ForecastRecordSet</value>
        <value name="field_type">recref</value>
        <value name="field_dim">0</value>
        <value name="nillable">true</value>
        <value name="form_qualified">false</value>
        <value name="is_global">false</value>
        <value name="modifiable">true</value>
        <value name="rec_ref">masterScheduling1213.intoOA.forecast.rec:setForecastTxnInputRec</value>
      </record>
    </array>
    <value name="modifiable">true</value>
  </record>
</Values>
</MAPSOURCE>

  <!-- nodes -->

<MAPCOPY NAME="Link" FROM="/ForecastRecordSet;4;0;masterScheduling1213.intoOA.forecast.rec:setForecastTxnInputRec" TO="/setForecastTxnInput;2;0">
</MAPCOPY>
</MAP>

<MAP MODE="OUTPUT">
  <MAPTARGET>

<Values version="2.0">
  <record name="xml" javaclass="com.wm.util.Values">
    <value name="node_type">record</value>
    <value name="is_public">false</value>
    <value name="field_type">record</value>
    <value name="field_dim">0</value>
    <value name="nillable">true</value>
    <value name="form_qualified">false</value>
    <value name="is_global">false</value>
    <array name="rec_fields" type="record" depth="1">
      <record javaclass="com.wm.util.Values">
        <value name="node_type">record</value>
        <value name="is_public">false</value>
        <value name="field_name">setForecastTxnInput</value>
        <value name="field_type">record</value>
        <value name="field_dim">0</value>
        <value name="nillable">true</value>
        <value name="form_qualified">false</value>
        <value name="is_global">false</value>
        <array name="rec_fields" type="record" depth="1">
        </array>
        <value name="modifiable">true</value>
      </record>
      <record javaclass="com.wm.util.Values">
        <value name="node_type">unknown</value>
        <value name="is_public">false</value>
        <value name="field_name">$dbAlias</value>
        <value name="field_type">string</value>
        <value name="field_dim">0</value>
        <value name="nillable">true</value>
        <value name="form_qualified">false</value>
        <value name="is_global">false</value>
      </record>
      <record javaclass="com.wm.util.Values">
        <value name="node_type">record</value>
        <value name="is_public">false</value>
        <value name="field_name">ForecastRecordSet</value>
        <value name="field_type">recref</value>
        <value name="field_dim">0</value>
        <value name="nillable">true</value>
        <value name="form_qualified">false</value>
        <value name="is_global">false</value>
        <value name="modifiable">true</value>
        <value name="rec_ref">masterScheduling1213.intoOA.forecast.rec:setForecastTxnInputRec</value>
      </record>
      <record javaclass="com.wm.util.Values">
        <value name="node_type">record</value>
        <value name="is_public">false</value>
        <value name="field_name">setForecastTxnOutput</value>
        <value name="field_type">record</value>
        <value name="field_dim">0</value>
        <value name="nillable">true</value>
        <value name="form_qualified">false</value>
        <value name="is_global">false</value>
        <array name="rec_fields" type="record" depth="1">
        </array>
        <value name="modifiable">true</value>
      </record>
    </array>
    <value name="modifiable">true</value>
  </record>
</Values>
</MAPTARGET>
  <MAPSOURCE>

<Values version="2.0">
  <record name="xml" javaclass="com.wm.util.Values">
    <value name="node_type">record</value>
    <value name="is_public">false</value>
    <value name="field_type">record</value>
    <value name="field_dim">0</value>
    <value name="nillable">true</value>
    <value name="form_qualified">false</value>
    <value name="is_global">false</value>
    <array name="rec_fields" type="record" depth="1">
    </array>
    <value name="modifiable">true</value>
  </record>
</Values>
</MAPSOURCE>

  <!-- nodes -->

<MAPDELETE NAME="Dropper" FIELD="/setForecastTxnInput;2;0">
</MAPDELETE>

<MAPDELETE NAME="Dropper" FIELD="/$dbAlias;1;0">
</MAPDELETE>

<MAPDELETE NAME="Dropper" FIELD="/ForecastRecordSet;4;0;masterScheduling1213.intoOA.forecast.rec:setForecastTxnInputRec">
</MAPDELETE>
</MAP>
</INVOKE>
</SEQUENCE>

<SEQUENCE TIMEOUT="" EXIT-ON="DONE">
  <COMMENT>Error Handling Sequence - exit on done</COMMENT>

  <!-- nodes -->

<INVOKE TIMEOUT="" SERVICE="pub.flow:getLastError" VALIDATE-IN="$none" VALIDATE-OUT="$none">
  <COMMENT></COMMENT>

  <!-- nodes -->

<MAP MODE="INPUT">
</MAP>

<MAP MODE="OUTPUT">
</MAP>
</INVOKE>
</SEQUENCE>
</SEQUENCE>
</FLOW>
