<?xml version="1.0" encoding="UTF-8"?>

<FLOW VERSION="3.0" CLEANUP="true">
  <COMMENT>Specify all the default settings</COMMENT>

  <!-- nodes -->

<MAP NAME="specifyDefaultSettings" TIMEOUT="" MODE="STANDALONE">
  <COMMENT>Specify all the default settings</COMMENT>
  <MAPTARGET>

<Values version="2.0">
  <record name="xml" javaclass="com.wm.util.Values">
    <value name="node_type">record</value>
    <value name="field_type">record</value>
    <value name="field_dim">0</value>
    <value name="field_opt">false</value>
    <array name="rec_fields" type="record" depth="1">
      <record javaclass="com.wm.util.Values">
        <value name="node_type">unknown</value>
        <value name="field_name">$dbAlias</value>
        <value name="field_type">string</value>
        <value name="field_dim">0</value>
        <value name="field_opt">false</value>
      </record>
      <record javaclass="com.wm.util.Values">
        <value name="node_type">unknown</value>
        <value name="field_name">noOfRowsToFetch</value>
        <value name="field_type">string</value>
        <value name="field_dim">0</value>
        <value name="field_opt">false</value>
      </record>
      <record javaclass="com.wm.util.Values">
        <value name="node_type">unknown</value>
        <value name="field_name">debugMode</value>
        <value name="field_type">string</value>
        <value name="field_dim">0</value>
        <value name="field_opt">false</value>
      </record>
    </array>
    <value name="rec_closed">false</value>
  </record>
</Values>
</MAPTARGET>
  <MAPSOURCE>

<Values version="2.0">
  <record name="xml" javaclass="com.wm.util.Values">
    <value name="node_type">record</value>
    <value name="field_type">record</value>
    <value name="field_dim">0</value>
    <value name="field_opt">false</value>
    <list name="rec_fields">
    </list>
    <value name="rec_closed">false</value>
  </record>
</Values>
</MAPSOURCE>

  <!-- nodes -->

<MAPSET NAME="Setter" OVERWRITE="true" VARIABLES="false" FIELD="/noOfRowsToFetch;1;0">
  <DATA ENCODING="XMLValues" I18N="true">

<Values version="2.0">
  <value name="xml">100000</value>
  <record name="type" javaclass="com.wm.util.Values">
    <value name="node_type">record</value>
    <value name="field_name">noOfRowsToFetch</value>
    <value name="field_type">string</value>
    <value name="field_dim">0</value>
    <value name="field_opt">false</value>
  </record>
</Values>
</DATA>
</MAPSET>

<MAPSET NAME="Setter" OVERWRITE="true" VARIABLES="false" FIELD="/debugMode;1;0">
  <DATA ENCODING="XMLValues" I18N="true">

<Values version="2.0">
  <value name="xml">FALSE</value>
  <record name="type" javaclass="com.wm.util.Values">
    <value name="node_type">record</value>
    <value name="field_name">debugMode</value>
    <value name="field_type">string</value>
    <value name="field_dim">0</value>
    <value name="field_opt">false</value>
  </record>
</Values>
</DATA>
</MAPSET>

<MAPSET NAME="Setter" OVERWRITE="true" VARIABLES="false" FIELD="/$dbAlias;1;0">
  <DATA ENCODING="XMLValues" I18N="true">

<Values version="2.0">
  <value name="xml">OraApps107SC</value>
  <record name="type" javaclass="com.wm.util.Values">
    <value name="node_type">record</value>
    <value name="field_name">$dbAlias</value>
    <value name="field_type">string</value>
    <value name="field_dim">0</value>
    <value name="field_opt">false</value>
  </record>
</Values>
</DATA>
</MAPSET>
</MAP>

<INVOKE TIMEOUT="" SERVICE="commonOA107SC.utils:lockTxnCtrl" VALIDATE-IN="$none" VALIDATE-OUT="$none">
  <COMMENT>Lock &amp; Update the Wm_Control Table to disable execution of same serivce when other session of service is in progress</COMMENT>

  <!-- nodes -->

<MAP MODE="INPUT">
  <MAPTARGET>

<Values version="2.0">
  <record name="xml" javaclass="com.wm.util.Values">
    <value name="node_type">record</value>
    <value name="field_name">in</value>
    <value name="field_type">record</value>
    <value name="field_dim">0</value>
    <value name="field_opt">false</value>
    <array name="rec_fields" type="record" depth="1">
      <record javaclass="com.wm.util.Values">
        <value name="node_type">record</value>
        <value name="field_name">queryParams</value>
        <value name="field_type">record</value>
        <value name="field_dim">0</value>
        <value name="field_opt">false</value>
        <array name="rec_fields" type="record" depth="1">
          <record javaclass="com.wm.util.Values">
            <value name="node_type">unknown</value>
            <value name="field_name">P_TRANSACTION_TYPE</value>
            <value name="field_type">string</value>
            <value name="field_dim">0</value>
            <value name="field_opt">false</value>
          </record>
        </array>
        <value name="rec_closed">false</value>
      </record>
      <record javaclass="com.wm.util.Values">
        <value name="node_type">record</value>
        <value name="field_name">$dbAlias</value>
        <value name="field_type">string</value>
        <value name="field_dim">0</value>
        <value name="field_opt">false</value>
      </record>
    </array>
    <value name="rec_closed">false</value>
  </record>
</Values>
</MAPTARGET>
  <MAPSOURCE>

<Values version="2.0">
  <record name="xml" javaclass="com.wm.util.Values">
    <value name="node_type">record</value>
    <value name="field_type">record</value>
    <value name="field_dim">0</value>
    <value name="field_opt">false</value>
    <list name="rec_fields">
    </list>
    <value name="rec_closed">false</value>
  </record>
</Values>
</MAPSOURCE>

  <!-- nodes -->

<MAPSET NAME="Setter" OVERWRITE="true" VARIABLES="false" FIELD="/queryParams;2;0">
  <DATA ENCODING="XMLValues" I18N="true">

<Values version="2.0">
  <record name="xml" javaclass="com.wm.util.Values">
    <value name="P_TRANSACTION_TYPE">MFGBOM</value>
  </record>
  <record name="type" javaclass="com.wm.util.Values">
    <value name="node_type">record</value>
    <value name="field_name">queryParams</value>
    <value name="field_type">record</value>
    <value name="field_dim">0</value>
    <value name="field_opt">false</value>
    <list name="rec_fields">
      <record javaclass="com.wm.util.Values">
        <value name="node_type">unknown</value>
        <value name="field_name">P_TRANSACTION_TYPE</value>
        <value name="field_type">string</value>
        <value name="field_dim">0</value>
        <value name="field_opt">false</value>
      </record>
    </list>
    <value name="rec_closed">false</value>
  </record>
</Values>
</DATA>
</MAPSET>
</MAP>

<MAP MODE="OUTPUT">
  <MAPTARGET>

<Values version="2.0">
  <record name="xml" javaclass="com.wm.util.Values">
    <value name="node_type">record</value>
    <value name="field_type">record</value>
    <value name="field_dim">0</value>
    <value name="field_opt">false</value>
    <array name="rec_fields" type="record" depth="1">
      <record javaclass="com.wm.util.Values">
        <value name="node_type">record</value>
        <value name="field_name">results</value>
        <value name="field_type">record</value>
        <value name="field_dim">0</value>
        <value name="field_opt">false</value>
        <list name="rec_fields">
        </list>
        <value name="rec_closed">false</value>
      </record>
      <record javaclass="com.wm.util.Values">
        <value name="node_type">record</value>
        <value name="field_name">queryParams</value>
        <value name="field_type">record</value>
        <value name="field_dim">0</value>
        <value name="field_opt">false</value>
        <array name="rec_fields" type="record" depth="1">
          <record javaclass="com.wm.util.Values">
            <value name="node_type">unknown</value>
            <value name="field_name">P_TRANSACTION_TYPE</value>
            <value name="field_type">string</value>
            <value name="field_dim">0</value>
            <value name="field_opt">false</value>
          </record>
        </array>
        <value name="rec_closed">false</value>
      </record>
      <record javaclass="com.wm.util.Values">
        <value name="node_type">unknown</value>
        <value name="field_name">$dbAlias</value>
        <value name="field_type">string</value>
        <value name="field_dim">0</value>
        <value name="field_opt">false</value>
      </record>
      <record javaclass="com.wm.util.Values">
        <value name="node_type">unknown</value>
        <value name="field_name">noOfRowsToFetch</value>
        <value name="field_type">string</value>
        <value name="field_dim">0</value>
        <value name="field_opt">false</value>
      </record>
      <record javaclass="com.wm.util.Values">
        <value name="node_type">unknown</value>
        <value name="field_name">debugMode</value>
        <value name="field_type">string</value>
        <value name="field_dim">0</value>
        <value name="field_opt">false</value>
      </record>
      <record javaclass="com.wm.util.Values">
        <value name="node_type">unknown</value>
        <value name="field_name">O_RETURN_STATUS</value>
        <value name="field_type">string</value>
        <value name="field_dim">0</value>
        <value name="field_opt">false</value>
      </record>
      <record javaclass="com.wm.util.Values">
        <value name="node_type">unknown</value>
        <value name="field_name">status</value>
        <value name="field_type">string</value>
        <value name="field_dim">0</value>
        <value name="field_opt">false</value>
      </record>
    </array>
    <value name="rec_closed">false</value>
  </record>
</Values>
</MAPTARGET>
  <MAPSOURCE>

<Values version="2.0">
  <record name="xml" javaclass="com.wm.util.Values">
    <value name="node_type">record</value>
    <value name="field_name">out</value>
    <value name="field_type">record</value>
    <value name="field_dim">0</value>
    <value name="field_opt">false</value>
    <array name="rec_fields" type="record" depth="1">
      <record javaclass="com.wm.util.Values">
        <value name="node_type">unknown</value>
        <value name="field_name">O_RETURN_STATUS</value>
        <value name="field_type">string</value>
        <value name="field_dim">0</value>
        <value name="field_opt">false</value>
      </record>
    </array>
    <value name="rec_closed">false</value>
  </record>
</Values>
</MAPSOURCE>

  <!-- nodes -->

<MAPDELETE NAME="Dropper" FIELD="/queryParams;2;0">
</MAPDELETE>

<MAPDELETE NAME="Dropper" FIELD="/results;2;0">
</MAPDELETE>

<MAPDELETE NAME="Dropper" FIELD="/O_RETURN_STATUS;1;0">
</MAPDELETE>

<MAPCOPY NAME="Link" FROM="/O_RETURN_STATUS;1;0" TO="/status;1;0">
</MAPCOPY>
</MAP>
</INVOKE>

<SEQUENCE TIMEOUT="" EXIT-ON="SUCCESS">
  <COMMENT>Main Sequence for Try/Catch Block</COMMENT>

  <!-- nodes -->

<SEQUENCE TIMEOUT="" EXIT-ON="FAILURE">
  <COMMENT>Execution Block</COMMENT>

  <!-- nodes -->

<BRANCH TIMEOUT="" SWITCH="/status">
  <COMMENT></COMMENT>

  <!-- nodes -->

<SEQUENCE NAME="TRUE" TIMEOUT="" EXIT-ON="FAILURE">
  <COMMENT></COMMENT>

  <!-- nodes -->

<INVOKE TIMEOUT="" SERVICE="billsOfMaterial107SC.fromOA.manufacturingBOM.custom:getManufacturingBOMTxn" VALIDATE-IN="$none" VALIDATE-OUT="$none">
  <COMMENT></COMMENT>

  <!-- nodes -->

<MAP MODE="INPUT">
  <MAPTARGET>

<Values version="2.0">
  <record name="xml" javaclass="com.wm.util.Values">
    <value name="node_type">record</value>
    <value name="field_name">in</value>
    <value name="field_type">record</value>
    <value name="field_dim">0</value>
    <value name="field_opt">false</value>
    <array name="rec_fields" type="record" depth="1">
      <record javaclass="com.wm.util.Values">
        <value name="node_type">record</value>
        <value name="field_name">queryParams</value>
        <value name="field_type">record</value>
        <value name="field_dim">0</value>
        <value name="field_opt">false</value>
        <array name="rec_fields" type="record" depth="1">
          <record javaclass="com.wm.util.Values">
            <value name="node_type">unknown</value>
            <value name="field_name">RECORDS_TO_FETCH</value>
            <value name="field_type">string</value>
            <value name="field_dim">0</value>
            <value name="field_opt">false</value>
          </record>
        </array>
        <value name="rec_closed">false</value>
      </record>
      <record javaclass="com.wm.util.Values">
        <value name="node_type">record</value>
        <value name="field_name">$dbAlias</value>
        <value name="field_type">string</value>
        <value name="field_dim">0</value>
        <value name="field_opt">false</value>
      </record>
    </array>
    <value name="rec_closed">false</value>
  </record>
</Values>
</MAPTARGET>
  <MAPSOURCE>

<Values version="2.0">
  <record name="xml" javaclass="com.wm.util.Values">
    <value name="node_type">record</value>
    <value name="field_type">record</value>
    <value name="field_dim">0</value>
    <value name="field_opt">false</value>
    <array name="rec_fields" type="record" depth="1">
      <record javaclass="com.wm.util.Values">
        <value name="node_type">unknown</value>
        <value name="field_name">$dbAlias</value>
        <value name="field_type">string</value>
        <value name="field_dim">0</value>
        <value name="field_opt">false</value>
      </record>
      <record javaclass="com.wm.util.Values">
        <value name="node_type">unknown</value>
        <value name="field_name">noOfRowsToFetch</value>
        <value name="field_type">string</value>
        <value name="field_dim">0</value>
        <value name="field_opt">false</value>
      </record>
      <record javaclass="com.wm.util.Values">
        <value name="node_type">unknown</value>
        <value name="field_name">debugMode</value>
        <value name="field_type">string</value>
        <value name="field_dim">0</value>
        <value name="field_opt">false</value>
      </record>
      <record javaclass="com.wm.util.Values">
        <value name="node_type">unknown</value>
        <value name="field_name">status</value>
        <value name="field_type">string</value>
        <value name="field_dim">0</value>
        <value name="field_opt">false</value>
      </record>
    </array>
    <value name="rec_closed">false</value>
  </record>
</Values>
</MAPSOURCE>

  <!-- nodes -->

<MAPCOPY NAME="Link" FROM="/noOfRowsToFetch;1;0" TO="/queryParams;2;0/RECORDS_TO_FETCH;1;0">
</MAPCOPY>
</MAP>

<MAP MODE="OUTPUT">
  <MAPTARGET>

<Values version="2.0">
  <record name="xml" javaclass="com.wm.util.Values">
    <value name="node_type">record</value>
    <value name="field_type">record</value>
    <value name="field_dim">0</value>
    <value name="field_opt">false</value>
    <array name="rec_fields" type="record" depth="1">
      <record javaclass="com.wm.util.Values">
        <value name="node_type">record</value>
        <value name="field_name">queryParams</value>
        <value name="field_type">record</value>
        <value name="field_dim">0</value>
        <value name="field_opt">false</value>
        <array name="rec_fields" type="record" depth="1">
          <record javaclass="com.wm.util.Values">
            <value name="node_type">unknown</value>
            <value name="field_name">RECORDS_TO_FETCH</value>
            <value name="field_type">string</value>
            <value name="field_dim">0</value>
            <value name="field_opt">false</value>
          </record>
        </array>
        <value name="rec_closed">false</value>
      </record>
      <record javaclass="com.wm.util.Values">
        <value name="node_type">unknown</value>
        <value name="field_name">$dbAlias</value>
        <value name="field_type">string</value>
        <value name="field_dim">0</value>
        <value name="field_opt">false</value>
      </record>
      <record javaclass="com.wm.util.Values">
        <value name="node_type">unknown</value>
        <value name="field_name">noOfRowsToFetch</value>
        <value name="field_type">string</value>
        <value name="field_dim">0</value>
        <value name="field_opt">false</value>
      </record>
      <record javaclass="com.wm.util.Values">
        <value name="node_type">unknown</value>
        <value name="field_name">debugMode</value>
        <value name="field_type">string</value>
        <value name="field_dim">0</value>
        <value name="field_opt">false</value>
      </record>
      <record javaclass="com.wm.util.Values">
        <value name="node_type">unknown</value>
        <value name="field_name">status</value>
        <value name="field_type">string</value>
        <value name="field_dim">0</value>
        <value name="field_opt">false</value>
      </record>
      <record javaclass="com.wm.util.Values">
        <value name="node_type">record</value>
        <value name="field_name">results</value>
        <value name="field_type">record</value>
        <value name="field_dim">0</value>
        <value name="field_opt">false</value>
        <array name="rec_fields" type="record" depth="1">
          <record javaclass="com.wm.util.Values">
            <value name="node_type">record</value>
            <value name="field_name">BOM_BILL_OF_MTLS</value>
            <value name="field_type">record</value>
            <value name="field_dim">1</value>
            <value name="field_opt">false</value>
            <list name="rec_fields">
            </list>
            <value name="rec_closed">false</value>
          </record>
        </array>
        <value name="rec_closed">false</value>
      </record>
      <record javaclass="com.wm.util.Values">
        <value name="node_type">unknown</value>
        <value name="field_name">message</value>
        <value name="field_type">string</value>
        <value name="field_dim">0</value>
        <value name="field_opt">false</value>
      </record>
      <record javaclass="com.wm.util.Values">
        <value name="node_type">record</value>
        <value name="field_name">mfgBOMResults</value>
        <value name="field_type">recref</value>
        <value name="field_dim">0</value>
        <value name="field_opt">false</value>
        <value name="rec_closed">false</value>
        <value name="rec_ref">BOM1157.fromOA.manufacturingBOM.rec:getManufacturingBOMTxnOutputRec</value>
      </record>
    </array>
    <value name="rec_closed">false</value>
  </record>
</Values>
</MAPTARGET>
  <MAPSOURCE>

<Values version="2.0">
  <record name="xml" javaclass="com.wm.util.Values">
    <value name="node_type">record</value>
    <value name="field_name">out</value>
    <value name="field_type">record</value>
    <value name="field_dim">0</value>
    <value name="field_opt">false</value>
    <array name="rec_fields" type="record" depth="1">
      <record javaclass="com.wm.util.Values">
        <value name="node_type">record</value>
        <value name="field_name">results</value>
        <value name="field_type">record</value>
        <value name="field_dim">0</value>
        <value name="field_opt">false</value>
        <array name="rec_fields" type="record" depth="1">
          <record javaclass="com.wm.util.Values">
            <value name="node_type">record</value>
            <value name="field_name">BOM_BILL_OF_MTLS</value>
            <value name="field_type">record</value>
            <value name="field_dim">1</value>
            <value name="field_opt">false</value>
            <list name="rec_fields">
            </list>
            <value name="rec_closed">false</value>
          </record>
        </array>
        <value name="rec_closed">false</value>
      </record>
      <record javaclass="com.wm.util.Values">
        <value name="node_type">unknown</value>
        <value name="field_name">message</value>
        <value name="field_type">string</value>
        <value name="field_dim">0</value>
        <value name="field_opt">false</value>
      </record>
    </array>
    <value name="rec_closed">false</value>
  </record>
</Values>
</MAPSOURCE>

  <!-- nodes -->

<MAPDELETE NAME="Dropper" FIELD="/noOfRowsToFetch;1;0">
</MAPDELETE>

<MAPCOPY NAME="Link" FROM="/results;2;0" TO="/mfgBOMResults;4;0;billsOfMaterial107SC.fromOA.manufacturingBOM.rec:getManufacturingBOMTxnOutputRec">
</MAPCOPY>

<MAPDELETE NAME="Dropper" FIELD="/results;2;0">
</MAPDELETE>

<MAPDELETE NAME="Dropper" FIELD="/message;1;0">
</MAPDELETE>

<MAPDELETE NAME="Dropper" FIELD="/status;1;0">
</MAPDELETE>

<MAPDELETE NAME="Dropper" FIELD="/queryParams;2;0">
</MAPDELETE>
</MAP>
</INVOKE>

<INVOKE TIMEOUT="" SERVICE="billsOfMaterial107SC.fromOA.manufacturingBOM.custom:processBizDoc" VALIDATE-IN="$none" VALIDATE-OUT="$none">
  <COMMENT></COMMENT>

  <!-- nodes -->

<MAP MODE="INPUT">
</MAP>

<MAP MODE="OUTPUT">
</MAP>
</INVOKE>

<LOOP TIMEOUT="" IN-ARRAY="/docTransferResults">
  <COMMENT></COMMENT>

  <!-- nodes -->

<SEQUENCE TIMEOUT="" EXIT-ON="FAILURE">
  <COMMENT></COMMENT>

  <!-- nodes -->

<BRANCH TIMEOUT="" SWITCH="/debugMode">
  <COMMENT></COMMENT>

  <!-- nodes -->

<INVOKE NAME="TRUE" TIMEOUT="" SERVICE="commonOA107SC.utils:updateTrackChanges" VALIDATE-IN="$none" VALIDATE-OUT="$none">
  <COMMENT></COMMENT>

  <!-- nodes -->

<MAP MODE="INPUT">
  <MAPTARGET>

<Values version="2.0">
  <record name="xml" javaclass="com.wm.util.Values">
    <value name="node_type">record</value>
    <value name="field_type">record</value>
    <value name="field_dim">0</value>
    <value name="field_opt">false</value>
    <array name="rec_fields" type="record" depth="1">
      <record javaclass="com.wm.util.Values">
        <value name="node_type">record</value>
        <value name="field_name">dataRecord</value>
        <value name="field_type">record</value>
        <value name="field_dim">0</value>
        <value name="field_opt">false</value>
        <array name="rec_fields" type="record" depth="1">
          <record javaclass="com.wm.util.Values">
            <value name="node_type">unknown</value>
            <value name="field_name">TRANSACTION_ID</value>
            <value name="field_type">string</value>
            <value name="field_dim">0</value>
            <value name="field_opt">false</value>
          </record>
          <record javaclass="com.wm.util.Values">
            <value name="node_type">unknown</value>
            <value name="field_name">WEB_TRANSACTION_ID</value>
            <value name="field_type">string</value>
            <value name="field_dim">0</value>
            <value name="field_opt">false</value>
          </record>
          <record javaclass="com.wm.util.Values">
            <value name="node_type">unknown</value>
            <value name="field_name">TRANSACTION_TYPE</value>
            <value name="field_type">string</value>
            <value name="field_dim">0</value>
            <value name="field_opt">false</value>
          </record>
        </array>
        <value name="rec_closed">false</value>
      </record>
    </array>
    <value name="rec_closed">false</value>
  </record>
</Values>
</MAPTARGET>
  <MAPSOURCE>

<Values version="2.0">
  <record name="xml" javaclass="com.wm.util.Values">
    <value name="node_type">record</value>
    <value name="field_type">record</value>
    <value name="field_dim">0</value>
    <value name="field_opt">false</value>
    <array name="rec_fields" type="record" depth="1">
      <record javaclass="com.wm.util.Values">
        <value name="node_type">unknown</value>
        <value name="field_name">$dbAlias</value>
        <value name="field_type">string</value>
        <value name="field_dim">0</value>
        <value name="field_opt">false</value>
      </record>
      <record javaclass="com.wm.util.Values">
        <value name="node_type">unknown</value>
        <value name="field_name">debugMode</value>
        <value name="field_type">string</value>
        <value name="field_dim">0</value>
        <value name="field_opt">false</value>
      </record>
      <record javaclass="com.wm.util.Values">
        <value name="node_type">record</value>
        <value name="node_comment"></value>
        <record name="node_hints" javaclass="com.wm.util.Values">
          <value name="field_largerEditor">false</value>
          <value name="field_password">false</value>
        </record>
        <value name="field_name">docTransferResults</value>
        <value name="field_type">recref</value>
        <value name="field_dim">0</value>
        <value name="field_opt">false</value>
        <value name="rec_closed">false</value>
        <value name="rec_ref">commonOA107SC.rec:docTransferResults</value>
      </record>
      <record javaclass="com.wm.util.Values">
        <value name="node_type">unknown</value>
        <value name="field_name">$iteration</value>
        <value name="field_type">string</value>
        <value name="field_dim">0</value>
        <value name="field_opt">false</value>
      </record>
    </array>
    <value name="rec_closed">false</value>
  </record>
</Values>
</MAPSOURCE>

  <!-- nodes -->

<MAPCOPY NAME="Link" FROM="/docTransferResults;2;0/TRANSACTION_ID;1;0" TO="/dataRecord;2;0/TRANSACTION_ID;1;0">
</MAPCOPY>

<MAPCOPY NAME="Link" FROM="/docTransferResults;4;0;commonOA107SC.rec:docTransferResults/WEB_TRANSACTION_ID;1;0" TO="/dataRecord;2;0/WEB_TRANSACTION_ID;1;0">
</MAPCOPY>

<MAPCOPY NAME="Link" FROM="/docTransferResults;4;0;commonOA107SC.rec:docTransferResults/DOCUMENT_TYPE;1;0" TO="/dataRecord;2;0/TRANSACTION_TYPE;1;0">
</MAPCOPY>
</MAP>

<MAP MODE="OUTPUT">
  <MAPTARGET>

<Values version="2.0">
  <record name="xml" javaclass="com.wm.util.Values">
    <value name="node_type">record</value>
    <value name="field_type">record</value>
    <value name="field_dim">0</value>
    <value name="field_opt">false</value>
    <array name="rec_fields" type="record" depth="1">
      <record javaclass="com.wm.util.Values">
        <value name="node_type">record</value>
        <value name="field_name">dataRecord</value>
        <value name="field_type">record</value>
        <value name="field_dim">0</value>
        <value name="field_opt">false</value>
        <array name="rec_fields" type="record" depth="1">
          <record javaclass="com.wm.util.Values">
            <value name="node_type">unknown</value>
            <value name="field_name">WEB_TRANSACTION_ID</value>
            <value name="field_type">string</value>
            <value name="field_dim">0</value>
            <value name="field_opt">false</value>
          </record>
          <record javaclass="com.wm.util.Values">
            <value name="node_type">unknown</value>
            <value name="field_name">TRANSACTION_TYPE</value>
            <value name="field_type">string</value>
            <value name="field_dim">0</value>
            <value name="field_opt">false</value>
          </record>
          <record javaclass="com.wm.util.Values">
            <value name="node_type">unknown</value>
            <value name="field_name">TRANSACTION_ID</value>
            <value name="field_type">string</value>
            <value name="field_dim">0</value>
            <value name="field_opt">false</value>
          </record>
        </array>
        <value name="rec_closed">false</value>
      </record>
      <record javaclass="com.wm.util.Values">
        <value name="node_type">unknown</value>
        <value name="field_name">$dbAlias</value>
        <value name="field_type">string</value>
        <value name="field_dim">0</value>
        <value name="field_opt">false</value>
      </record>
      <record javaclass="com.wm.util.Values">
        <value name="node_type">unknown</value>
        <value name="field_name">debugMode</value>
        <value name="field_type">string</value>
        <value name="field_dim">0</value>
        <value name="field_opt">false</value>
      </record>
      <record javaclass="com.wm.util.Values">
        <value name="node_type">record</value>
        <value name="node_comment"></value>
        <record name="node_hints" javaclass="com.wm.util.Values">
          <value name="field_largerEditor">false</value>
          <value name="field_password">false</value>
        </record>
        <value name="field_name">docTransferResults</value>
        <value name="field_type">recref</value>
        <value name="field_dim">0</value>
        <value name="field_opt">false</value>
        <value name="rec_closed">false</value>
        <value name="rec_ref">commonOA107SC.rec:docTransferResults</value>
      </record>
    </array>
    <value name="rec_closed">false</value>
  </record>
</Values>
</MAPTARGET>
  <MAPSOURCE>

<Values version="2.0">
  <record name="xml" javaclass="com.wm.util.Values">
    <value name="node_type">record</value>
    <value name="field_type">record</value>
    <value name="field_dim">0</value>
    <value name="field_opt">false</value>
    <list name="rec_fields">
    </list>
    <value name="rec_closed">false</value>
  </record>
</Values>
</MAPSOURCE>

  <!-- nodes -->

<MAPDELETE NAME="Dropper" FIELD="/dataRecord;2;0">
</MAPDELETE>
</MAP>
</INVOKE>

<INVOKE NAME="FALSE" TIMEOUT="" SERVICE="commonOA107SC.utils:purgeTrackChanges" VALIDATE-IN="$none" VALIDATE-OUT="$none">
  <COMMENT></COMMENT>

  <!-- nodes -->

<MAP MODE="INPUT">
  <MAPTARGET>

<Values version="2.0">
  <record name="xml" javaclass="com.wm.util.Values">
    <value name="node_type">record</value>
    <value name="field_name">in</value>
    <value name="field_type">record</value>
    <value name="field_dim">0</value>
    <value name="field_opt">false</value>
    <array name="rec_fields" type="record" depth="1">
      <record javaclass="com.wm.util.Values">
        <value name="node_type">record</value>
        <value name="field_name">dataRecord</value>
        <value name="field_type">record</value>
        <value name="field_dim">0</value>
        <value name="field_opt">false</value>
        <array name="rec_fields" type="record" depth="1">
          <record javaclass="com.wm.util.Values">
            <value name="node_type">unknown</value>
            <value name="field_name">WEB_TRANSACTION_ID</value>
            <value name="field_type">string</value>
            <value name="field_dim">0</value>
            <value name="field_opt">false</value>
          </record>
          <record javaclass="com.wm.util.Values">
            <value name="node_type">unknown</value>
            <value name="field_name">TRANSACTION_TYPE</value>
            <value name="field_type">string</value>
            <value name="field_dim">0</value>
            <value name="field_opt">false</value>
          </record>
          <record javaclass="com.wm.util.Values">
            <value name="node_type">unknown</value>
            <value name="field_name">TRANSACTION_ID</value>
            <value name="field_type">string</value>
            <value name="field_dim">0</value>
            <value name="field_opt">false</value>
          </record>
        </array>
        <value name="rec_closed">false</value>
      </record>
      <record javaclass="com.wm.util.Values">
        <value name="node_type">record</value>
        <value name="field_name">$dbAlias</value>
        <value name="field_type">string</value>
        <value name="field_dim">0</value>
        <value name="field_opt">false</value>
      </record>
    </array>
    <value name="rec_closed">false</value>
  </record>
</Values>
</MAPTARGET>
  <MAPSOURCE>

<Values version="2.0">
  <record name="xml" javaclass="com.wm.util.Values">
    <value name="node_type">record</value>
    <value name="field_type">record</value>
    <value name="field_dim">0</value>
    <value name="field_opt">false</value>
    <array name="rec_fields" type="record" depth="1">
      <record javaclass="com.wm.util.Values">
        <value name="node_type">unknown</value>
        <value name="field_name">$dbAlias</value>
        <value name="field_type">string</value>
        <value name="field_dim">0</value>
        <value name="field_opt">false</value>
      </record>
      <record javaclass="com.wm.util.Values">
        <value name="node_type">unknown</value>
        <value name="field_name">debugMode</value>
        <value name="field_type">string</value>
        <value name="field_dim">0</value>
        <value name="field_opt">false</value>
      </record>
      <record javaclass="com.wm.util.Values">
        <value name="node_type">record</value>
        <value name="field_name">vendorResults</value>
        <value name="field_type">recref</value>
        <value name="field_dim">0</value>
        <value name="field_opt">false</value>
        <value name="rec_closed">false</value>
        <value name="rec_ref">payables107SC.fromOA.vendor.rec:getVendorTxnOutputRec</value>
      </record>
      <record javaclass="com.wm.util.Values">
        <value name="node_type">record</value>
        <value name="field_name">docTransferResults</value>
        <value name="field_type">record</value>
        <value name="field_dim">0</value>
        <value name="field_opt">false</value>
        <array name="rec_fields" type="record" depth="1">
          <record javaclass="com.wm.util.Values">
            <value name="node_type">unknown</value>
            <value name="field_name">WEB_TRANSACTION_ID</value>
            <value name="field_type">string</value>
            <value name="field_dim">0</value>
            <value name="field_opt">false</value>
          </record>
          <record javaclass="com.wm.util.Values">
            <value name="node_type">unknown</value>
            <value name="field_name">DOCUMENT_TYPE</value>
            <value name="field_type">string</value>
            <value name="field_dim">0</value>
            <value name="field_opt">false</value>
          </record>
          <record javaclass="com.wm.util.Values">
            <value name="node_type">unknown</value>
            <value name="field_name">DOCUMENT_STATUS</value>
            <value name="field_type">string</value>
            <value name="field_dim">0</value>
            <value name="field_opt">false</value>
          </record>
          <record javaclass="com.wm.util.Values">
            <value name="node_type">unknown</value>
            <value name="field_name">TRANSACTION_ID</value>
            <value name="field_type">string</value>
            <value name="field_dim">0</value>
            <value name="field_opt">false</value>
          </record>
          <record javaclass="com.wm.util.Values">
            <value name="node_type">unknown</value>
            <value name="field_name">transferStatus</value>
            <value name="field_type">string</value>
            <value name="field_dim">0</value>
            <value name="field_opt">false</value>
          </record>
          <record javaclass="com.wm.util.Values">
            <value name="node_type">record</value>
            <value name="field_name">errorInfo</value>
            <value name="field_type">string</value>
            <value name="field_dim">0</value>
            <value name="field_opt">false</value>
          </record>
        </array>
        <value name="rec_closed">false</value>
      </record>
      <record javaclass="com.wm.util.Values">
        <value name="node_type">unknown</value>
        <value name="field_name">$iteration</value>
        <value name="field_type">string</value>
        <value name="field_dim">0</value>
        <value name="field_opt">false</value>
      </record>
    </array>
    <value name="rec_closed">false</value>
  </record>
</Values>
</MAPSOURCE>

  <!-- nodes -->

<MAPCOPY NAME="Link" FROM="/docTransferResults;2;0/WEB_TRANSACTION_ID;1;0" TO="/dataRecord;2;0/WEB_TRANSACTION_ID;1;0">
</MAPCOPY>

<MAPCOPY NAME="Link" FROM="/docTransferResults;2;0/DOCUMENT_TYPE;1;0" TO="/dataRecord;2;0/TRANSACTION_TYPE;1;0">
</MAPCOPY>

<MAPCOPY NAME="Link" FROM="/docTransferResults;2;0/TRANSACTION_ID;1;0" TO="/dataRecord;2;0/TRANSACTION_ID;1;0">
</MAPCOPY>
</MAP>

<MAP MODE="OUTPUT">
  <MAPTARGET>

<Values version="2.0">
  <record name="xml" javaclass="com.wm.util.Values">
    <value name="node_type">record</value>
    <value name="field_type">record</value>
    <value name="field_dim">0</value>
    <value name="field_opt">false</value>
    <array name="rec_fields" type="record" depth="1">
      <record javaclass="com.wm.util.Values">
        <value name="node_type">record</value>
        <value name="field_name">dataRecord</value>
        <value name="field_type">record</value>
        <value name="field_dim">0</value>
        <value name="field_opt">false</value>
        <array name="rec_fields" type="record" depth="1">
          <record javaclass="com.wm.util.Values">
            <value name="node_type">unknown</value>
            <value name="field_name">WEB_TRANSACTION_ID</value>
            <value name="field_type">string</value>
            <value name="field_dim">0</value>
            <value name="field_opt">false</value>
          </record>
          <record javaclass="com.wm.util.Values">
            <value name="node_type">unknown</value>
            <value name="field_name">TRANSACTION_TYPE</value>
            <value name="field_type">string</value>
            <value name="field_dim">0</value>
            <value name="field_opt">false</value>
          </record>
          <record javaclass="com.wm.util.Values">
            <value name="node_type">unknown</value>
            <value name="field_name">TRANSACTION_ID</value>
            <value name="field_type">string</value>
            <value name="field_dim">0</value>
            <value name="field_opt">false</value>
          </record>
        </array>
        <value name="rec_closed">false</value>
      </record>
      <record javaclass="com.wm.util.Values">
        <value name="node_type">unknown</value>
        <value name="field_name">$dbAlias</value>
        <value name="field_type">string</value>
        <value name="field_dim">0</value>
        <value name="field_opt">false</value>
      </record>
      <record javaclass="com.wm.util.Values">
        <value name="node_type">unknown</value>
        <value name="field_name">debugMode</value>
        <value name="field_type">string</value>
        <value name="field_dim">0</value>
        <value name="field_opt">false</value>
      </record>
      <record javaclass="com.wm.util.Values">
        <value name="node_type">record</value>
        <value name="field_name">vendorResults</value>
        <value name="field_type">recref</value>
        <value name="field_dim">0</value>
        <value name="field_opt">false</value>
        <value name="rec_closed">false</value>
        <value name="rec_ref">payables107SC.fromOA.vendor.rec:getVendorTxnOutputRec</value>
      </record>
      <record javaclass="com.wm.util.Values">
        <value name="node_type">record</value>
        <value name="field_name">docTransferResults</value>
        <value name="field_type">record</value>
        <value name="field_dim">0</value>
        <value name="field_opt">false</value>
        <list name="rec_fields">
        </list>
        <value name="rec_closed">false</value>
      </record>
      <record javaclass="com.wm.util.Values">
        <value name="node_type">record</value>
        <value name="field_name">results</value>
        <value name="field_type">record</value>
        <value name="field_dim">1</value>
        <value name="field_opt">false</value>
        <list name="rec_fields">
        </list>
        <value name="rec_closed">false</value>
      </record>
    </array>
    <value name="rec_closed">false</value>
  </record>
</Values>
</MAPTARGET>
  <MAPSOURCE>

<Values version="2.0">
  <record name="xml" javaclass="com.wm.util.Values">
    <value name="node_type">record</value>
    <value name="field_type">record</value>
    <value name="field_dim">0</value>
    <value name="field_opt">false</value>
    <list name="rec_fields">
    </list>
    <value name="rec_closed">false</value>
  </record>
</Values>
</MAPSOURCE>

  <!-- nodes -->

<MAPDELETE NAME="Dropper" FIELD="/dataRecord;2;0">
</MAPDELETE>
</MAP>
</INVOKE>
</BRANCH>

<BRANCH TIMEOUT="" SWITCH="/docTransferResults/transferStatus">
  <COMMENT></COMMENT>

  <!-- nodes -->

<INVOKE NAME="ERROR" TIMEOUT="" SERVICE="commonOA107SC.utils:insertTransferERRInfo" VALIDATE-IN="$none" VALIDATE-OUT="$none">
  <COMMENT>Insert New Record at the End</COMMENT>

  <!-- nodes -->

<MAP MODE="INPUT">
</MAP>

<MAP MODE="OUTPUT">
</MAP>
</INVOKE>

<EXIT NAME="SUCCESS" FROM="$parent" SIGNAL="SUCCESS" FAILURE-MESSAGE="">
  <COMMENT>Do Nothing</COMMENT>
</EXIT>
</BRANCH>
</SEQUENCE>
</LOOP>

<BRANCH TIMEOUT="" SWITCH="/debugMode">
  <COMMENT></COMMENT>

  <!-- nodes -->

<INVOKE NAME="TRUE" TIMEOUT="" SERVICE="commonOA107SC.utils:updateUnqualifiedRec" VALIDATE-IN="$none" VALIDATE-OUT="$none">
  <COMMENT></COMMENT>

  <!-- nodes -->

<MAP MODE="INPUT">
  <MAPTARGET>

<Values version="2.0">
  <record name="xml" javaclass="com.wm.util.Values">
    <value name="node_type">record</value>
    <value name="field_name">in</value>
    <value name="field_type">record</value>
    <value name="field_dim">0</value>
    <value name="field_opt">false</value>
    <array name="rec_fields" type="record" depth="1">
      <record javaclass="com.wm.util.Values">
        <value name="node_type">record</value>
        <value name="field_name">dataRecord</value>
        <value name="field_type">record</value>
        <value name="field_dim">0</value>
        <value name="field_opt">false</value>
        <array name="rec_fields" type="record" depth="1">
          <record javaclass="com.wm.util.Values">
            <value name="node_type">unknown</value>
            <value name="field_name">TRANSACTION_TYPE</value>
            <value name="field_type">string</value>
            <value name="field_dim">0</value>
            <value name="field_opt">false</value>
          </record>
        </array>
        <value name="rec_closed">false</value>
      </record>
      <record javaclass="com.wm.util.Values">
        <value name="node_type">unknown</value>
        <value name="node_comment"></value>
        <record name="node_hints" javaclass="com.wm.util.Values">
          <null name="field_usereditable"/>
          <value name="field_largerEditor">false</value>
          <value name="field_password">false</value>
        </record>
        <value name="field_name">$dbAlias</value>
        <value name="field_type">string</value>
        <value name="field_dim">0</value>
        <value name="field_opt">false</value>
      </record>
    </array>
    <value name="rec_closed">false</value>
  </record>
</Values>
</MAPTARGET>
  <MAPSOURCE>

<Values version="2.0">
  <record name="xml" javaclass="com.wm.util.Values">
    <value name="node_type">record</value>
    <value name="field_type">record</value>
    <value name="field_dim">0</value>
    <value name="field_opt">false</value>
    <list name="rec_fields">
    </list>
    <value name="rec_closed">false</value>
  </record>
</Values>
</MAPSOURCE>

  <!-- nodes -->

<MAPSET NAME="Setter" OVERWRITE="true" VARIABLES="false" FIELD="/dataRecord;2;0">
  <DATA ENCODING="XMLValues" I18N="true">

<Values version="2.0">
  <record name="xml" javaclass="com.wm.util.Values">
    <value name="TRANSACTION_TYPE">MFGBOM</value>
  </record>
  <record name="type" javaclass="com.wm.util.Values">
    <value name="node_type">record</value>
    <value name="field_name">dataRecord</value>
    <value name="field_type">record</value>
    <value name="field_dim">0</value>
    <value name="field_opt">false</value>
    <list name="rec_fields">
      <record javaclass="com.wm.util.Values">
        <value name="node_type">unknown</value>
        <value name="field_name">TRANSACTION_TYPE</value>
        <value name="field_type">string</value>
        <value name="field_dim">0</value>
        <value name="field_opt">false</value>
      </record>
    </list>
    <value name="rec_closed">false</value>
  </record>
</Values>
</DATA>
</MAPSET>
</MAP>

<MAP MODE="OUTPUT">
  <MAPTARGET>

<Values version="2.0">
  <record name="xml" javaclass="com.wm.util.Values">
    <value name="node_type">record</value>
    <value name="field_type">record</value>
    <value name="field_dim">0</value>
    <value name="field_opt">false</value>
    <array name="rec_fields" type="record" depth="1">
      <record javaclass="com.wm.util.Values">
        <value name="node_type">record</value>
        <value name="field_name">dataRecord</value>
        <value name="field_type">record</value>
        <value name="field_dim">0</value>
        <value name="field_opt">false</value>
        <list name="rec_fields">
        </list>
        <value name="rec_closed">false</value>
      </record>
      <record javaclass="com.wm.util.Values">
        <value name="node_type">unknown</value>
        <value name="field_name">$dbAlias</value>
        <value name="field_type">string</value>
        <value name="field_dim">0</value>
        <value name="field_opt">false</value>
      </record>
      <record javaclass="com.wm.util.Values">
        <value name="node_type">unknown</value>
        <value name="field_name">debugMode</value>
        <value name="field_type">string</value>
        <value name="field_dim">0</value>
        <value name="field_opt">false</value>
      </record>
      <record javaclass="com.wm.util.Values">
        <value name="node_type">record</value>
        <value name="field_name">mfgBOMResults</value>
        <value name="field_type">recref</value>
        <value name="field_dim">0</value>
        <value name="field_opt">false</value>
        <value name="rec_closed">false</value>
        <value name="rec_ref">billsOfMaterial107SC.fromOA.manufacturingBOM.rec:getManufacturingBOMTxnOutputRec</value>
      </record>
      <record javaclass="com.wm.util.Values">
        <value name="node_type">record</value>
        <value name="node_comment"></value>
        <record name="node_hints" javaclass="com.wm.util.Values">
          <value name="field_largerEditor">false</value>
          <value name="field_password">false</value>
        </record>
        <value name="field_name">docTransferResults</value>
        <value name="field_type">recref</value>
        <value name="field_dim">1</value>
        <value name="field_opt">false</value>
        <value name="rec_closed">false</value>
        <value name="rec_ref">commonOA107SC.rec:docTransferResults</value>
      </record>
    </array>
    <value name="rec_closed">false</value>
  </record>
</Values>
</MAPTARGET>
  <MAPSOURCE>

<Values version="2.0">
  <record name="xml" javaclass="com.wm.util.Values">
    <value name="node_type">record</value>
    <value name="field_type">record</value>
    <value name="field_dim">0</value>
    <value name="field_opt">false</value>
    <list name="rec_fields">
    </list>
    <value name="rec_closed">false</value>
  </record>
</Values>
</MAPSOURCE>

  <!-- nodes -->

<MAPDELETE NAME="Dropper" FIELD="/dataRecord;2;0">
</MAPDELETE>
</MAP>
</INVOKE>

<INVOKE NAME="FALSE" TIMEOUT="" SERVICE="commonOA107SC.utils:purgeUnqualifiedRec" VALIDATE-IN="$none" VALIDATE-OUT="$none">
  <COMMENT></COMMENT>

  <!-- nodes -->

<MAP MODE="INPUT">
  <MAPTARGET>

<Values version="2.0">
  <record name="xml" javaclass="com.wm.util.Values">
    <value name="node_type">record</value>
    <value name="field_name">in</value>
    <value name="field_type">record</value>
    <value name="field_dim">0</value>
    <value name="field_opt">false</value>
    <array name="rec_fields" type="record" depth="1">
      <record javaclass="com.wm.util.Values">
        <value name="node_type">record</value>
        <value name="field_name">dataRecord</value>
        <value name="field_type">record</value>
        <value name="field_dim">0</value>
        <value name="field_opt">false</value>
        <array name="rec_fields" type="record" depth="1">
          <record javaclass="com.wm.util.Values">
            <value name="node_type">unknown</value>
            <value name="field_name">TRANSACTION_TYPE</value>
            <value name="field_type">string</value>
            <value name="field_dim">0</value>
            <value name="field_opt">false</value>
          </record>
        </array>
        <value name="rec_closed">false</value>
      </record>
      <record javaclass="com.wm.util.Values">
        <value name="node_type">unknown</value>
        <value name="node_comment"></value>
        <record name="node_hints" javaclass="com.wm.util.Values">
          <null name="field_usereditable"/>
          <value name="field_largerEditor">false</value>
          <value name="field_password">false</value>
        </record>
        <value name="field_name">$dbAlias</value>
        <value name="field_type">string</value>
        <value name="field_dim">0</value>
        <value name="field_opt">false</value>
      </record>
    </array>
    <value name="rec_closed">false</value>
  </record>
</Values>
</MAPTARGET>
  <MAPSOURCE>

<Values version="2.0">
  <record name="xml" javaclass="com.wm.util.Values">
    <value name="node_type">record</value>
    <value name="field_type">record</value>
    <value name="field_dim">0</value>
    <value name="field_opt">false</value>
    <list name="rec_fields">
    </list>
    <value name="rec_closed">false</value>
  </record>
</Values>
</MAPSOURCE>

  <!-- nodes -->

<MAPSET NAME="Setter" OVERWRITE="true" VARIABLES="false" FIELD="/dataRecord;2;0">
  <DATA ENCODING="XMLValues" I18N="true">

<Values version="2.0">
  <record name="xml" javaclass="com.wm.util.Values">
    <value name="TRANSACTION_TYPE">MFGBOM</value>
  </record>
  <record name="type" javaclass="com.wm.util.Values">
    <value name="node_type">record</value>
    <value name="field_name">dataRecord</value>
    <value name="field_type">record</value>
    <value name="field_dim">0</value>
    <value name="field_opt">false</value>
    <list name="rec_fields">
      <record javaclass="com.wm.util.Values">
        <value name="node_type">unknown</value>
        <value name="field_name">TRANSACTION_TYPE</value>
        <value name="field_type">string</value>
        <value name="field_dim">0</value>
        <value name="field_opt">false</value>
      </record>
    </list>
    <value name="rec_closed">false</value>
  </record>
</Values>
</DATA>
</MAPSET>
</MAP>

<MAP MODE="OUTPUT">
  <MAPTARGET>

<Values version="2.0">
  <record name="xml" javaclass="com.wm.util.Values">
    <value name="node_type">record</value>
    <value name="field_type">record</value>
    <value name="field_dim">0</value>
    <value name="field_opt">false</value>
    <array name="rec_fields" type="record" depth="1">
      <record javaclass="com.wm.util.Values">
        <value name="node_type">record</value>
        <value name="field_name">dataRecord</value>
        <value name="field_type">record</value>
        <value name="field_dim">0</value>
        <value name="field_opt">false</value>
        <list name="rec_fields">
        </list>
        <value name="rec_closed">false</value>
      </record>
      <record javaclass="com.wm.util.Values">
        <value name="node_type">unknown</value>
        <value name="field_name">$dbAlias</value>
        <value name="field_type">string</value>
        <value name="field_dim">0</value>
        <value name="field_opt">false</value>
      </record>
      <record javaclass="com.wm.util.Values">
        <value name="node_type">unknown</value>
        <value name="field_name">debugMode</value>
        <value name="field_type">string</value>
        <value name="field_dim">0</value>
        <value name="field_opt">false</value>
      </record>
      <record javaclass="com.wm.util.Values">
        <value name="node_type">record</value>
        <value name="field_name">mfgBOMResults</value>
        <value name="field_type">recref</value>
        <value name="field_dim">0</value>
        <value name="field_opt">false</value>
        <value name="rec_closed">false</value>
        <value name="rec_ref">billsOfMaterial107SC.fromOA.manufacturingBOM.rec:getManufacturingBOMTxnOutputRec</value>
      </record>
      <record javaclass="com.wm.util.Values">
        <value name="node_type">record</value>
        <value name="node_comment"></value>
        <record name="node_hints" javaclass="com.wm.util.Values">
          <value name="field_largerEditor">false</value>
          <value name="field_password">false</value>
        </record>
        <value name="field_name">docTransferResults</value>
        <value name="field_type">recref</value>
        <value name="field_dim">1</value>
        <value name="field_opt">false</value>
        <value name="rec_closed">false</value>
        <value name="rec_ref">commonOA107SC.rec:docTransferResults</value>
      </record>
    </array>
    <value name="rec_closed">false</value>
  </record>
</Values>
</MAPTARGET>
  <MAPSOURCE>

<Values version="2.0">
  <record name="xml" javaclass="com.wm.util.Values">
    <value name="node_type">record</value>
    <value name="field_type">record</value>
    <value name="field_dim">0</value>
    <value name="field_opt">false</value>
    <list name="rec_fields">
    </list>
    <value name="rec_closed">false</value>
  </record>
</Values>
</MAPSOURCE>

  <!-- nodes -->

<MAPDELETE NAME="Dropper" FIELD="/dataRecord;2;0">
</MAPDELETE>
</MAP>
</INVOKE>
</BRANCH>

<INVOKE TIMEOUT="" SERVICE="commonOA107SC.utils:unlockTxnCtrl" VALIDATE-IN="$none" VALIDATE-OUT="$none">
  <COMMENT></COMMENT>

  <!-- nodes -->

<MAP MODE="INPUT">
  <MAPTARGET>

<Values version="2.0">
  <record name="xml" javaclass="com.wm.util.Values">
    <value name="node_type">record</value>
    <value name="field_name">in</value>
    <value name="field_type">record</value>
    <value name="field_dim">0</value>
    <value name="field_opt">false</value>
    <array name="rec_fields" type="record" depth="1">
      <record javaclass="com.wm.util.Values">
        <value name="node_type">record</value>
        <value name="field_name">dataRecord</value>
        <value name="field_type">record</value>
        <value name="field_dim">0</value>
        <value name="field_opt">false</value>
        <array name="rec_fields" type="record" depth="1">
          <record javaclass="com.wm.util.Values">
            <value name="node_type">unknown</value>
            <value name="field_name">TRANSACTION_TYPE</value>
            <value name="field_type">string</value>
            <value name="field_dim">0</value>
            <value name="field_opt">false</value>
          </record>
        </array>
        <value name="rec_closed">false</value>
      </record>
      <record javaclass="com.wm.util.Values">
        <value name="node_type">record</value>
        <value name="field_name">$dbAlias</value>
        <value name="field_type">string</value>
        <value name="field_dim">0</value>
        <value name="field_opt">false</value>
      </record>
    </array>
    <value name="rec_closed">false</value>
  </record>
</Values>
</MAPTARGET>
  <MAPSOURCE>

<Values version="2.0">
  <record name="xml" javaclass="com.wm.util.Values">
    <value name="node_type">record</value>
    <value name="field_type">record</value>
    <value name="field_dim">0</value>
    <value name="field_opt">false</value>
    <list name="rec_fields">
    </list>
    <value name="rec_closed">false</value>
  </record>
</Values>
</MAPSOURCE>

  <!-- nodes -->

<MAPSET NAME="Setter" OVERWRITE="true" VARIABLES="false" FIELD="/dataRecord;2;0">
  <DATA ENCODING="XMLValues" I18N="true">

<Values version="2.0">
  <record name="xml" javaclass="com.wm.util.Values">
    <value name="TRANSACTION_TYPE">MFGBOM</value>
  </record>
  <record name="type" javaclass="com.wm.util.Values">
    <value name="node_type">record</value>
    <value name="field_name">dataRecord</value>
    <value name="field_type">record</value>
    <value name="field_dim">0</value>
    <value name="field_opt">false</value>
    <list name="rec_fields">
      <record javaclass="com.wm.util.Values">
        <value name="node_type">unknown</value>
        <value name="field_name">TRANSACTION_TYPE</value>
        <value name="field_type">string</value>
        <value name="field_dim">0</value>
        <value name="field_opt">false</value>
      </record>
    </list>
    <value name="rec_closed">false</value>
  </record>
</Values>
</DATA>
</MAPSET>
</MAP>

<MAP MODE="OUTPUT">
  <MAPTARGET>

<Values version="2.0">
  <record name="xml" javaclass="com.wm.util.Values">
    <value name="node_type">record</value>
    <value name="field_type">record</value>
    <value name="field_dim">0</value>
    <value name="field_opt">false</value>
    <array name="rec_fields" type="record" depth="1">
      <record javaclass="com.wm.util.Values">
        <value name="node_type">record</value>
        <value name="field_name">dataRecord</value>
        <value name="field_type">record</value>
        <value name="field_dim">0</value>
        <value name="field_opt">false</value>
        <array name="rec_fields" type="record" depth="1">
          <record javaclass="com.wm.util.Values">
            <value name="node_type">unknown</value>
            <value name="field_name">TRANSACTION_TYPE</value>
            <value name="field_type">string</value>
            <value name="field_dim">0</value>
            <value name="field_opt">false</value>
          </record>
        </array>
        <value name="rec_closed">false</value>
      </record>
      <record javaclass="com.wm.util.Values">
        <value name="node_type">unknown</value>
        <value name="field_name">$dbAlias</value>
        <value name="field_type">string</value>
        <value name="field_dim">0</value>
        <value name="field_opt">false</value>
      </record>
      <record javaclass="com.wm.util.Values">
        <value name="node_type">unknown</value>
        <value name="field_name">debugMode</value>
        <value name="field_type">string</value>
        <value name="field_dim">0</value>
        <value name="field_opt">false</value>
      </record>
      <record javaclass="com.wm.util.Values">
        <value name="node_type">record</value>
        <value name="field_name">mfgBOMResults</value>
        <value name="field_type">recref</value>
        <value name="field_dim">0</value>
        <value name="field_opt">false</value>
        <value name="rec_closed">false</value>
        <value name="rec_ref">billsOfMaterial107SC.fromOA.manufacturingBOM.rec:getManufacturingBOMTxnOutputRec</value>
      </record>
      <record javaclass="com.wm.util.Values">
        <value name="node_type">record</value>
        <value name="node_comment"></value>
        <record name="node_hints" javaclass="com.wm.util.Values">
          <value name="field_largerEditor">false</value>
          <value name="field_password">false</value>
        </record>
        <value name="field_name">docTransferResults</value>
        <value name="field_type">recref</value>
        <value name="field_dim">1</value>
        <value name="field_opt">false</value>
        <value name="rec_closed">false</value>
        <value name="rec_ref">commonOA107SC.rec:docTransferResults</value>
      </record>
    </array>
    <value name="rec_closed">false</value>
  </record>
</Values>
</MAPTARGET>
  <MAPSOURCE>

<Values version="2.0">
  <record name="xml" javaclass="com.wm.util.Values">
    <value name="node_type">record</value>
    <value name="field_type">record</value>
    <value name="field_dim">0</value>
    <value name="field_opt">false</value>
    <list name="rec_fields">
    </list>
    <value name="rec_closed">false</value>
  </record>
</Values>
</MAPSOURCE>

  <!-- nodes -->

<MAPDELETE NAME="Dropper" FIELD="/dataRecord;2;0">
</MAPDELETE>

<MAPDELETE NAME="Dropper" FIELD="/$dbAlias;1;0">
</MAPDELETE>

<MAPDELETE NAME="Dropper" FIELD="/debugMode;1;0">
</MAPDELETE>

<MAPDELETE NAME="Dropper" FIELD="/docTransferResults;4;1;commonOA107SC.rec:docTransferResults">
</MAPDELETE>
</MAP>
</INVOKE>
</SEQUENCE>

<SEQUENCE NAME="FALSE" TIMEOUT="" EXIT-ON="FAILURE">
  <COMMENT></COMMENT>

  <!-- nodes -->

<MAP MODE="STANDALONE">
  <COMMENT>Remove unwanted variables</COMMENT>
  <MAPTARGET>

<Values version="2.0">
  <record name="xml" javaclass="com.wm.util.Values">
    <value name="node_type">record</value>
    <value name="field_type">record</value>
    <value name="field_dim">0</value>
    <value name="field_opt">false</value>
    <list name="rec_fields">
    </list>
    <value name="rec_closed">false</value>
  </record>
</Values>
</MAPTARGET>
  <MAPSOURCE>

<Values version="2.0">
  <record name="xml" javaclass="com.wm.util.Values">
    <value name="node_type">record</value>
    <value name="field_type">record</value>
    <value name="field_dim">0</value>
    <value name="field_opt">false</value>
    <array name="rec_fields" type="record" depth="1">
      <record javaclass="com.wm.util.Values">
        <value name="node_type">unknown</value>
        <value name="field_name">$dbAlias</value>
        <value name="field_type">string</value>
        <value name="field_dim">0</value>
        <value name="field_opt">false</value>
      </record>
      <record javaclass="com.wm.util.Values">
        <value name="node_type">unknown</value>
        <value name="field_name">status</value>
        <value name="field_type">string</value>
        <value name="field_dim">0</value>
        <value name="field_opt">false</value>
      </record>
      <record javaclass="com.wm.util.Values">
        <value name="node_type">unknown</value>
        <value name="field_name">noOfRowsToFetch</value>
        <value name="field_type">string</value>
        <value name="field_dim">0</value>
        <value name="field_opt">false</value>
      </record>
      <record javaclass="com.wm.util.Values">
        <value name="node_type">unknown</value>
        <value name="field_name">debugMode</value>
        <value name="field_type">string</value>
        <value name="field_dim">0</value>
        <value name="field_opt">false</value>
      </record>
    </array>
    <value name="rec_closed">false</value>
  </record>
</Values>
</MAPSOURCE>

  <!-- nodes -->

<MAPDELETE NAME="Dropper" FIELD="/status;1;0">
</MAPDELETE>

<MAPDELETE NAME="Dropper" FIELD="/$dbAlias;1;0">
</MAPDELETE>

<MAPDELETE NAME="Dropper" FIELD="/noOfRowsToFetch;1;0">
</MAPDELETE>

<MAPDELETE NAME="Dropper" FIELD="/debugMode;1;0">
</MAPDELETE>
</MAP>

<EXIT FROM="$parent" SIGNAL="SUCCESS" FAILURE-MESSAGE="">
  <COMMENT></COMMENT>
</EXIT>
</SEQUENCE>
</BRANCH>
</SEQUENCE>

<SEQUENCE TIMEOUT="" EXIT-ON="DONE">
  <COMMENT>Error Handling Block</COMMENT>

  <!-- nodes -->

<INVOKE TIMEOUT="" SERVICE="pub.flow:getLastError" VALIDATE-IN="$none" VALIDATE-OUT="$none">
  <COMMENT></COMMENT>

  <!-- nodes -->

<MAP MODE="INPUT">
</MAP>

<MAP MODE="OUTPUT">
</MAP>
</INVOKE>

<INVOKE TIMEOUT="" SERVICE="commonOA107SC.utils:unlockTxnCtrl" VALIDATE-IN="$none" VALIDATE-OUT="$none">
  <COMMENT></COMMENT>

  <!-- nodes -->

<MAP MODE="INPUT">
  <MAPTARGET>

<Values version="2.0">
  <record name="xml" javaclass="com.wm.util.Values">
    <value name="node_type">record</value>
    <value name="field_name">in</value>
    <value name="field_type">record</value>
    <value name="field_dim">0</value>
    <value name="field_opt">false</value>
    <array name="rec_fields" type="record" depth="1">
      <record javaclass="com.wm.util.Values">
        <value name="node_type">record</value>
        <value name="field_name">dataRecord</value>
        <value name="field_type">record</value>
        <value name="field_dim">0</value>
        <value name="field_opt">false</value>
        <array name="rec_fields" type="record" depth="1">
          <record javaclass="com.wm.util.Values">
            <value name="node_type">unknown</value>
            <value name="field_name">TRANSACTION_TYPE</value>
            <value name="field_type">string</value>
            <value name="field_dim">0</value>
            <value name="field_opt">false</value>
          </record>
        </array>
        <value name="rec_closed">false</value>
      </record>
      <record javaclass="com.wm.util.Values">
        <value name="node_type">record</value>
        <value name="field_name">$dbAlias</value>
        <value name="field_type">string</value>
        <value name="field_dim">0</value>
        <value name="field_opt">false</value>
      </record>
    </array>
    <value name="rec_closed">false</value>
  </record>
</Values>
</MAPTARGET>
  <MAPSOURCE>

<Values version="2.0">
  <record name="xml" javaclass="com.wm.util.Values">
    <value name="node_type">record</value>
    <value name="field_type">record</value>
    <value name="field_dim">0</value>
    <value name="field_opt">false</value>
    <array name="rec_fields" type="record" depth="1">
      <record javaclass="com.wm.util.Values">
        <value name="node_type">record</value>
        <value name="field_name">mfgBOMResults</value>
        <value name="field_type">recref</value>
        <value name="field_dim">0</value>
        <value name="field_opt">false</value>
        <value name="rec_closed">false</value>
        <value name="rec_ref">billsOfMaterial107SC.fromOA.manufacturingBOM.rec:getManufacturingBOMTxnOutputRec</value>
      </record>
      <record javaclass="com.wm.util.Values">
        <value name="node_type">unknown</value>
        <value name="field_name">$dbAlias</value>
        <value name="field_type">string</value>
        <value name="field_dim">0</value>
        <value name="field_opt">false</value>
      </record>
      <record javaclass="com.wm.util.Values">
        <value name="node_type">record</value>
        <value name="field_name">lastError</value>
        <value name="field_type">recref</value>
        <value name="field_dim">0</value>
        <value name="field_opt">false</value>
        <value name="rec_closed">false</value>
        <value name="rec_ref">pub.event:exceptionInfo</value>
      </record>
    </array>
    <value name="rec_closed">false</value>
  </record>
</Values>
</MAPSOURCE>

  <!-- nodes -->

<MAPSET NAME="Setter" OVERWRITE="true" VARIABLES="false" FIELD="/dataRecord;2;0">
  <DATA ENCODING="XMLValues" I18N="true">

<Values version="2.0">
  <record name="xml" javaclass="com.wm.util.Values">
    <value name="TRANSACTION_TYPE">MFGBOM</value>
  </record>
  <record name="type" javaclass="com.wm.util.Values">
    <value name="node_type">record</value>
    <value name="field_name">dataRecord</value>
    <value name="field_type">record</value>
    <value name="field_dim">0</value>
    <value name="field_opt">false</value>
    <list name="rec_fields">
      <record javaclass="com.wm.util.Values">
        <value name="node_type">unknown</value>
        <value name="field_name">TRANSACTION_TYPE</value>
        <value name="field_type">string</value>
        <value name="field_dim">0</value>
        <value name="field_opt">false</value>
      </record>
    </list>
    <value name="rec_closed">false</value>
  </record>
</Values>
</DATA>
</MAPSET>

<MAPCOPY NAME="Link" FROM="/$dbAlias;1;0" TO="/$dbAlias;1;0">
</MAPCOPY>
</MAP>

<MAP MODE="OUTPUT">
  <MAPTARGET>

<Values version="2.0">
  <record name="xml" javaclass="com.wm.util.Values">
    <value name="node_type">record</value>
    <value name="field_type">record</value>
    <value name="field_dim">0</value>
    <value name="field_opt">false</value>
    <array name="rec_fields" type="record" depth="1">
      <record javaclass="com.wm.util.Values">
        <value name="node_type">record</value>
        <value name="field_name">dataRecord</value>
        <value name="field_type">record</value>
        <value name="field_dim">0</value>
        <value name="field_opt">false</value>
        <array name="rec_fields" type="record" depth="1">
          <record javaclass="com.wm.util.Values">
            <value name="node_type">unknown</value>
            <value name="field_name">TRANSACTION_TYPE</value>
            <value name="field_type">string</value>
            <value name="field_dim">0</value>
            <value name="field_opt">false</value>
          </record>
        </array>
        <value name="rec_closed">false</value>
      </record>
      <record javaclass="com.wm.util.Values">
        <value name="node_type">record</value>
        <value name="field_name">mfgBOMResults</value>
        <value name="field_type">recref</value>
        <value name="field_dim">0</value>
        <value name="field_opt">false</value>
        <value name="rec_closed">false</value>
        <value name="rec_ref">billsOfMaterial107SC.fromOA.manufacturingBOM.rec:getManufacturingBOMTxnOutputRec</value>
      </record>
      <record javaclass="com.wm.util.Values">
        <value name="node_type">unknown</value>
        <value name="field_name">$dbAlias</value>
        <value name="field_type">string</value>
        <value name="field_dim">0</value>
        <value name="field_opt">false</value>
      </record>
      <record javaclass="com.wm.util.Values">
        <value name="node_type">record</value>
        <value name="field_name">lastError</value>
        <value name="field_type">recref</value>
        <value name="field_dim">0</value>
        <value name="field_opt">false</value>
        <value name="rec_closed">false</value>
        <value name="rec_ref">pub.event:exceptionInfo</value>
      </record>
    </array>
    <value name="rec_closed">false</value>
  </record>
</Values>
</MAPTARGET>
  <MAPSOURCE>

<Values version="2.0">
  <record name="xml" javaclass="com.wm.util.Values">
    <value name="node_type">record</value>
    <value name="field_type">record</value>
    <value name="field_dim">0</value>
    <value name="field_opt">false</value>
    <list name="rec_fields">
    </list>
    <value name="rec_closed">false</value>
  </record>
</Values>
</MAPSOURCE>

  <!-- nodes -->

<MAPDELETE NAME="Dropper" FIELD="/dataRecord;2;0">
</MAPDELETE>

<MAPDELETE NAME="Dropper" FIELD="/$dbAlias;1;0">
</MAPDELETE>
</MAP>
</INVOKE>
</SEQUENCE>
</SEQUENCE>
</FLOW>
